odoo8_addon_project_task_reassign-8.0.1.2.0-py2.7-nspkg.pth
odoo_addons/project_task_reassign/__openerp__.py
odoo_addons/project_task_reassign/project_task_view.xml
odoo_addons/project_task_reassign/project.py
odoo_addons/project_task_reassign/__init__.py
odoo_addons/project_task_reassign/README.rst
odoo_addons/project_task_reassign/wizard/project_task_reassign.py
odoo_addons/project_task_reassign/wizard/__init__.py
odoo_addons/project_task_reassign/wizard/project_task_reassign_view.xml
odoo8_addon_project_task_reassign-8.0.1.2.0.dist-info/top_level.txt
odoo8_addon_project_task_reassign-8.0.1.2.0.dist-info/WHEEL
odoo8_addon_project_task_reassign-8.0.1.2.0.dist-info/RECORD
odoo8_addon_project_task_reassign-8.0.1.2.0.dist-info/metadata.json
odoo8_addon_project_task_reassign-8.0.1.2.0.dist-info/DESCRIPTION.rst
odoo8_addon_project_task_reassign-8.0.1.2.0.dist-info/METADATA
odoo8_addon_project_task_reassign-8.0.1.2.0.dist-info/namespace_packages.txt
