Metadata-Version: 2.0
Name: odoo8-addon-project-task-reassign
Version: 8.0.1.2.0
Summary: Reassign Tasks to other Responsibles and Projects
Home-page: https://github.com/OCA/project
Author: Daniel Reis, Odoo Community Association (OCA)
Author-email: support@odoo-community.org
License: AGPL-3
Platform: UNKNOWN
Requires-Dist: odoo (<9.0a,>=8.0a)
Classifier: Programming Language :: Python :: 2.7
Classifier: Framework :: Odoo
Classifier: License :: OSI Approved :: GNU Affero General Public License v3
